scrapy_selenium4/__init__.py
scrapy_selenium4/http.py
scrapy_selenium4/middlewares.py
scrapy_selenium4-1.0.0.dist-info/LICENCE
scrapy_selenium4-1.0.0.dist-info/METADATA
scrapy_selenium4-1.0.0.dist-info/WHEEL
scrapy_selenium4-1.0.0.dist-info/top_level.txt
scrapy_selenium4-1.0.0.dist-info/RECORD
