Metadata-Version: 2.1
Name: scrapy-selenium4
Version: 1.0.0
Summary: Scrapy with selenium4.
Home-page: https://github.com/zhouyangchao/scrapy-selenium
Author: zhouyangchao
Author-email: zhouyates@gmail.com
License: MIT
Classifier: License :: OSI Approved :: MIT License
Classifier: Programming Language :: Python
Classifier: Programming Language :: Python :: 3
Classifier: Programming Language :: Python :: 3.6
Classifier: Programming Language :: Python :: Implementation :: CPython
Classifier: Programming Language :: Python :: Implementation :: PyPy
Requires-Python: >=3.6.0
License-File: LICENCE
Requires-Dist: Scrapy>=2.5.0
Requires-Dist: selenium>=4.0.0
